Metadata-Version: 1.1
Name: laminate
Version: 0.5
Summary: Tool for creating styled html and pdf from markup
Home-page: https://github.com/ohenrik/laminate
Author: Ole Henrik Skogstrøm
Author-email: laminate@amplify.no
License: UNKNOWN
Platform: UNKNOWN
Classifier: Development Status :: 2 - Pre-Alpha
